LICENSE.txt
MANIFEST.in
README.md
setup.cfg
setup.py
ojai/Document.py
ojai/DocumentStream.py
ojai/__init__.py
ojai/error/StoreError.py
ojai/error/UnsupportedConstructorException.py
ojai/error/__init__.py
ojai/store/Connection.py
ojai/store/DocumentMutation.py
ojai/store/DocumentStore.py
ojai/store/Query.py
ojai/store/QueryCondition.py
ojai/store/QueryResult.py
ojai/store/__init__.py
ojai/types/ODate.py
ojai/types/OInterval.py
ojai/types/OTime.py
ojai/types/OTimestamp.py
ojai/types/__init__.py
ojai/types/constants.py
ojai_python_api.egg-info/PKG-INFO
ojai_python_api.egg-info/SOURCES.txt
ojai_python_api.egg-info/dependency_links.txt
ojai_python_api.egg-info/requires.txt
ojai_python_api.egg-info/top_level.txt