Metadata-Version: 1.0
Name: ojai-python-api
Version: 1.1
Summary: OJAI Python APIs
Home-page: https://github.com/ojai/ojai/tree/master/python
Author: MapR, Inc.
Author-email: UNKNOWN
License: UNKNOWN
Keywords: ojai python api
Platform: UNKNOWN
